pyqt5UartTool/__init__.py
pyqt5UartTool/pyserial_demo.py
pyqt5UartTool/ui_demo_1.py
pyqt5_Uart_Tool-0.1.dist-info/METADATA
pyqt5_Uart_Tool-0.1.dist-info/WHEEL
pyqt5_Uart_Tool-0.1.dist-info/top_level.txt
pyqt5_Uart_Tool-0.1.dist-info/RECORD
